{
    "uid": "50010000041631",
    "tid": "00040000001AE100",
    "product_code": "CTR-N-AEVJ",
    "platform_name": "3DSカード/ダウンロードソフト",
    "rating_system": {
        "name": "CERO",
        "age": "15"
    },
    "descriptors": [],
    "release_date_on_eshop": "2017-05-11",
    "formal_name": "進撃の巨人　死地からの脱出",
    "description": "TVアニメ「進撃の巨人」が\"戦慄の脱出アドベンチャー\"となって登場!\n<br>物語の舞台は、人間を食らう脅威「巨人」がうごめく謎の古城。「進撃の巨人」のキャラクターたちとともに、いまだかつてなく絶望的な状況から生還を目指す緊張感あふれる脱出劇が展開します。\n<br>さらに、ビジュアルや舞台背景、キャラクターボイスはTVアニメ「進撃の巨人」の制作スタッフ・声優陣が担当。\n<br>追い詰められた極限状態で垣間見える仲間たちの意外な一面やエピソードをドラマチックに描き出します。",
    "name": "進撃の巨人　死地からの脱出",
    "genres": [
        "アドベンチャー"
    ],
    "features": [
        "インターネット対応",
        "Nintendo Network"
    ],
    "languages": [
        "日本語"
    ],
    "disclaimer": "本ソフトは3D表示に対応しておりません。",
    "version": "v0.2.0",
    "region": "Japan"
}