{
    "uid": "50010000042388",
    "tid": "000400000F70A100",
    "product_code": "KTR-N-CBPJ",
    "platform_name": "New 3DSダウンロードソフト",
    "rating_system": {
        "name": "CERO",
        "age": "0"
    },
    "descriptors": [],
    "release_date_on_eshop": "2017-02-22",
    "formal_name": "かいぞくポップ",
    "description": "まるで、レトロLCDポケットゲーム機をプレイしている懐かしい感覚が味わえる！　\n<br>悪名高きバブル海賊が島の人たちをバブルに閉じ込めてしまった！ 主人公「ピートJr」は愛用のイカリを片手に、彼らを倒すために立ち上がるのだった……バブルを避けながら、愛用のイカリでバブルを次々と割って、パワーアップアイテムを集めよう。ただし、敵は常に重力を操って攻撃を仕掛けてくるので、要注意。集めたコインで、音楽とキャラに加え、ゲーム内ショップでフェイスプレート、ボタン、バックライトの購入が可能。ポケットゲームを自分好みにカスタマイズができる。\n<br>さあ、バブル割りの航海に出発だ。イカリをあげろ！",
    "name": "かいぞくポップ",
    "genres": [
        "アクション",
        "シューティング"
    ],
    "features": [],
    "languages": [
        "日本語"
    ],
    "disclaimer": "本ソフトは3D表示に対応しておりません。"
}