{
    "uid": "50010000010873",
    "tid": "0004000000095B00",
    "product_code": "CTR-P-AKVJ",
    "platform_name": "ニンテンドー3DSカードソフト",
    "rating_system": {
        "name": "CERO",
        "age": "0"
    },
    "descriptors": [],
    "release_date_on_eshop": null,
    "formal_name": "こびとづかん こびと観察セット",
    "description": "人気の『こびとづかん』がニンテンドー3DSソフトで登場! 不思議な生きもの「コビト」たちを探して･捕まえて･観察して、自分だけの「こびと図鑑」を完成させましょう! 登場するコビトは全部で13種類! クサマダラオオコビト、リトルハナガシラ、カクレモモジリは、ケースに入れて観察することができます。\n<br>\n<br>● さがす!\n<br>家の周りや畑、農道などいろいろなところを探してみましょう。\n<br>\n<br>● つかまえる!\n<br>ワナを作って、コビトをつかまえましょう!\n<br>\n<br>● 観察する!\n<br>つかまえたコビトに快適な環境を作って、コビトのいろいろな生態を写真に撮りましょう!\n<br>\n<br>● あそぶ!\n<br>コビトと一緒に写真を撮ったり、自分や家族、お友達などをコビトに変身させてあそぶこともできます! 写真はSDカードに保存されるので、お友達に送ったり、ブログにアップしたりができます!",
    "name": "こびとづかん こびと観察セット",
    "genres": [
        "シミュレーション"
    ],
    "features": [
        "3D映像対応"
    ],
    "languages": [
        "日本語"
    ],
    "disclaimer": null
}